<?xml version="1.0"?>
<!DOCTYPE hibernate-mapping PUBLIC "-//Hibernate/Hibernate Mapping DTD 3.0//EN"
"http://hibernate.sourceforge.net/hibernate-mapping-3.0.dtd">
<!-- Generated Dec 5, 2013 10:12:30 PM by Hibernate Tools 3.4.0.CR1 -->
<hibernate-mapping>
    <class name="com.nsi.kanban.shared.pojo.KanbanCard" table="KANBANCARD">
        <id name="id" type="long" access="field">
            <column name="ID" />
            <generator class="assigned" />
        </id>
        <property name="quantity" type="java.lang.String">
            <column name="QUANTITY" />
        </property>
    </class>
</hibernate-mapping>
